CHANGELOG.rst
LICENSE
MANIFEST.in
README.rst
setup.py
src/abysmal/__init__.py
src/abysmal/compiler.py
src/abysmal/coverage.py
src/abysmal/dsm.c
src/abysmal.egg-info/PKG-INFO
src/abysmal.egg-info/SOURCES.txt
src/abysmal.egg-info/dependency_links.txt
src/abysmal.egg-info/not-zip-safe
src/abysmal.egg-info/top_level.txt