Metadata-Version: 1.2
Name: abysmal
Version: 1.2.0
Summary: Abysmal (Appallingly Basic Yet Somehow Mostly Adequate Language)
Home-page: https://github.com/zillow/abysmal
Author: John-Anthony Owens
Author-email: johnao@zillowgroup.com
License: MIT license
Keywords: absymal,programming,language
Platform: UNKNOWN
Classifier: Development Status :: 5 - Production/Stable
Classifier: Intended Audience :: Developers
Classifier: License :: OSI Approved :: MIT License
Classifier: Operating System :: POSIX :: Linux
Classifier: Programming Language :: Python
Classifier: Programming Language :: Python :: 3
Classifier: Programming Language :: Python :: 3.3
Classifier: Programming Language :: Python :: 3.4
Classifier: Programming Language :: Python :: 3.5
Classifier: Programming Language :: Python :: 3.6
Classifier: Programming Language :: Python :: Implementation :: CPython
Classifier: Topic :: Software Development :: Code Generators
Classifier: Topic :: Software Development :: Compilers
Classifier: Topic :: Software Development :: Interpreters
Requires-Python: >= 3.3
